flashML/__init__.py
flashML-0.0.3.dist-info/LICENCE.txt
flashML-0.0.3.dist-info/METADATA
flashML-0.0.3.dist-info/WHEEL
flashML-0.0.3.dist-info/top_level.txt
flashML-0.0.3.dist-info/RECORD
