Metadata-Version: 2.1
Name: flashML
Version: 0.0.3
Summary: AutoML tool
Home-page: https://github.com/omchaithanyav/flashML
Author: Om Chaithanya V, Sai Prakash Y
Author-email: vomchaithanya@gmail.com
License: MIT
Keywords: AutoML
Platform: UNKNOWN
Classifier: Development Status :: 5 - Production/Stable
Classifier: Intended Audience :: Education
Classifier: Operating System :: OS Independent
Classifier: License :: OSI Approved :: MIT License
Classifier: Programming Language :: Python :: 3
Requires-Python: >=3.6
License-File: LICENCE.txt
Requires-Dist: NumPy (>=1.16.2)
Requires-Dist: lightgbm (>=2.3.1)
Requires-Dist: scipy (>=1.4.1)
Requires-Dist: pandas (>=1.1.4)
Requires-Dist: scikit-learn (>=0.24)
Requires-Dist: catboost (>=0.26)
Requires-Dist: optuna
